geolime_jl/__init__.py
geolime_jl-1.2.0.dist-info/licenses/LICENSE
geolime_jl-1.2.0.dist-info/METADATA
geolime_jl-1.2.0.dist-info/WHEEL
geolime_jl-1.2.0.dist-info/top_level.txt
geolime_jl-1.2.0.dist-info/RECORD
