Metadata-Version: 2.4
Name: geolime_jl
Version: 1.2.0
Summary: GeoLime_jl is part of GeoLime ecosystem
Author-email: DeepLime <contact@deeplime.io>
Project-URL: Homepage, https://github.com/deeplime-io/geolime_jl-pypi-package
Project-URL: Repository, https://github.com/deeplime-io/geolime_jl-pypi-package
Keywords: geolime_jl,geolime,geostats
Classifier: Programming Language :: Python :: 3
Classifier: Operating System :: OS Independent
Requires-Python: >=3.8
License-File: LICENSE
Dynamic: license-file
